yandex_money
