Metadata-Version: 1.1
Name: yandex-money-sdk
Version: 0.1.3
Summary: SDK yandex money API
Home-page: UNKNOWN
Author: Anton Ermak
Author-email: ermak@yamoney.ru
License: MIT
Keywords: sdk yandex money
Platform: UNKNOWN
Classifier: Programming Language :: Python :: 3.4
Classifier: Programming Language :: Python :: 2.7
Classifier: Intended Audience :: Developers
Classifier: License :: OSI Approved :: MIT License
Classifier: Development Status :: 3 - Alpha
